{
    "/js/app.js": "/js/app.js?id=532b78cada3e145e3278",
    "/css/app.css": "/css/app.css?id=3b11ebb6a36c3b3c7bc0",
    "/Home.js": "/Home.js?id=50c894ca1a3fa1912e6f",
    "/NotFoundError.js": "/NotFoundError.js?id=d9351a6d3687c5a1674f",
    "/Profile.js": "/Profile.js?id=7924e91d0cd4a69d09ce",
    "/Profile~ShopDetail.js": "/Profile~ShopDetail.js?id=f0731a1fe1ea88419b96",
    "/ShopDetail.js": "/ShopDetail.js?id=9b31659321ff5815a2ea",
    "/ShopList.js": "/ShopList.js?id=68ce934c2f484c5c185e",
    "/ShopListByWards.js": "/ShopListByWards.js?id=451a744940f6daba6a29",
    "/ShopList~ShopListByWards.js": "/ShopList~ShopListByWards.js?id=df397914158a5d067c7b",
    "/SignIn.js": "/SignIn.js?id=02acdbe09138c203df4f",
    "/SignUp.js": "/SignUp.js?id=c604e77ce32009795d35",
    "/SystemError.js": "/SystemError.js?id=47ffbfee321632e6ca64",
    "/vendors~ShopList~ShopListByWards.js": "/vendors~ShopList~ShopListByWards.js?id=44eb2b191919a24293f3",
    "/vendors~ShopList.js": "/vendors~ShopList.js?id=699fe34b8f5ef7a3acfd"
}
